{
  "@context": ["https://doi.org/10.5063/schema/codemeta-2.0", "http://schema.org"],
  "@type": "SoftwareSourceCode",
  "identifier": "mctq",
  "description": "A complete and consistent toolkit to process the Munich ChronoType \n    Questionnaire (MCTQ) for its three versions (standard, micro, and shift). \n    MCTQ is a quantitative and validated tool to assess chronotypes using \n    peoples' sleep behavior, originally presented by Till Roenneberg, Anna \n    Wirz-Justice, and Martha Merrow (2003, <doi:10.1177/0748730402239679>).",
  "name": "mctq: Tools to Process the Munich ChronoType Questionnaire (MCTQ)",
  "codeRepository": "https://github.com/ropensci/mctq/",
  "relatedLink": "https://docs.ropensci.org/mctq/",
  "issueTracker": "https://github.com/ropensci/mctq/issues/",
  "license": "https://spdx.org/licenses/MIT",
  "version": "0.1.0",
  "programmingLanguage": {
    "@type": "ComputerLanguage",
    "name": "R",
    "url": "https://r-project.org"
  },
  "runtimePlatform": "R version 4.1.1 (2021-08-10)",
  "author": [
    {
      "@type": "Person",
      "givenName": "Daniel",
      "familyName": "Vartanian",
      "email": "danvartan@gmail.com",
      "@id": "https://orcid.org/0000-0001-7782-759X"
    },
    {
      "@type": "Person",
      "givenName": "Ana Amelia",
      "familyName": "Benedito-Silva",
      "email": "aamelia@usp.br",
      "@id": "https://orcid.org/0000-0003-4976-2623"
    },
    {
      "@type": "Person",
      "givenName": "Mario",
      "familyName": "Pedrazzoli",
      "email": "pedrazzo@usp.br",
      "@id": "https://orcid.org/0000-0002-5257-591X"
    }
  ],
  "contributor": {},
  "copyrightHolder": [
    {
      "@type": "Person",
      "givenName": "Daniel",
      "familyName": "Vartanian",
      "email": "danvartan@gmail.com",
      "@id": "https://orcid.org/0000-0001-7782-759X"
    }
  ],
  "funder": [
    {
      "@type": "Organization",
      "name": "Interdisciplinary Sleep Research Group (GIPSO)"
    },
    {
      "@type": "Organization",
      "name": "University of Sao Paulo (USP)"
    }
  ],
  "maintainer": [
    {
      "@type": "Person",
      "givenName": "Daniel",
      "familyName": "Vartanian",
      "email": "danvartan@gmail.com",
      "@id": "https://orcid.org/0000-0001-7782-759X"
    }
  ],
  "softwareSuggestions": [
    {
      "@type": "SoftwareApplication",
      "identifier": "covr",
      "name": "covr",
      "version": ">= 3.5.1",
      "provider": {
        "@id": "https://cran.r-project.org",
        "@type": "Organization",
        "name": "Comprehensive R Archive Network (CRAN)",
        "url": "https://cran.r-project.org"
      },
      "sameAs": "https://CRAN.R-project.org/package=covr"
    },
    {
      "@type": "SoftwareApplication",
      "identifier": "datasets",
      "name": "datasets",
      "version": ">= 4.0.0"
    },
    {
      "@type": "SoftwareApplication",
      "identifier": "ggplot2",
      "name": "ggplot2",
      "version": ">= 3.3.5",
      "provider": {
        "@id": "https://cran.r-project.org",
        "@type": "Organization",
        "name": "Comprehensive R Archive Network (CRAN)",
        "url": "https://cran.r-project.org"
      },
      "sameAs": "https://CRAN.R-project.org/package=ggplot2"
    },
    {
      "@type": "SoftwareApplication",
      "identifier": "grDevices",
      "name": "grDevices",
      "version": ">= 4.0.0"
    },
    {
      "@type": "SoftwareApplication",
      "identifier": "knitr",
      "name": "knitr",
      "version": ">= 1.36",
      "provider": {
        "@id": "https://cran.r-project.org",
        "@type": "Organization",
        "name": "Comprehensive R Archive Network (CRAN)",
        "url": "https://cran.r-project.org"
      },
      "sameAs": "https://CRAN.R-project.org/package=knitr"
    },
    {
      "@type": "SoftwareApplication",
      "identifier": "mockr",
      "name": "mockr",
      "version": ">= 0.1",
      "provider": {
        "@id": "https://cran.r-project.org",
        "@type": "Organization",
        "name": "Comprehensive R Archive Network (CRAN)",
        "url": "https://cran.r-project.org"
      },
      "sameAs": "https://CRAN.R-project.org/package=mockr"
    },
    {
      "@type": "SoftwareApplication",
      "identifier": "readr",
      "name": "readr",
      "version": ">= 2.0.2",
      "provider": {
        "@id": "https://cran.r-project.org",
        "@type": "Organization",
        "name": "Comprehensive R Archive Network (CRAN)",
        "url": "https://cran.r-project.org"
      },
      "sameAs": "https://CRAN.R-project.org/package=readr"
    },
    {
      "@type": "SoftwareApplication",
      "identifier": "rmarkdown",
      "name": "rmarkdown",
      "version": ">= 2.11",
      "provider": {
        "@id": "https://cran.r-project.org",
        "@type": "Organization",
        "name": "Comprehensive R Archive Network (CRAN)",
        "url": "https://cran.r-project.org"
      },
      "sameAs": "https://CRAN.R-project.org/package=rmarkdown"
    },
    {
      "@type": "SoftwareApplication",
      "identifier": "spelling",
      "name": "spelling",
      "version": ">= 2.2",
      "provider": {
        "@id": "https://cran.r-project.org",
        "@type": "Organization",
        "name": "Comprehensive R Archive Network (CRAN)",
        "url": "https://cran.r-project.org"
      },
      "sameAs": "https://CRAN.R-project.org/package=spelling"
    },
    {
      "@type": "SoftwareApplication",
      "identifier": "stats",
      "name": "stats",
      "version": ">= 4.0.0"
    },
    {
      "@type": "SoftwareApplication",
      "identifier": "testthat",
      "name": "testthat",
      "version": ">= 3.1.0",
      "provider": {
        "@id": "https://cran.r-project.org",
        "@type": "Organization",
        "name": "Comprehensive R Archive Network (CRAN)",
        "url": "https://cran.r-project.org"
      },
      "sameAs": "https://CRAN.R-project.org/package=testthat"
    },
    {
      "@type": "SoftwareApplication",
      "identifier": "usethis",
      "name": "usethis",
      "version": ">= 2.1.3",
      "provider": {
        "@id": "https://cran.r-project.org",
        "@type": "Organization",
        "name": "Comprehensive R Archive Network (CRAN)",
        "url": "https://cran.r-project.org"
      },
      "sameAs": "https://CRAN.R-project.org/package=usethis"
    },
    {
      "@type": "SoftwareApplication",
      "identifier": "utils",
      "name": "utils",
      "version": ">= 4.0.0"
    }
  ],
  "softwareRequirements": [
    {
      "@type": "SoftwareApplication",
      "identifier": "R",
      "name": "R",
      "version": ">= 4.0"
    },
    {
      "@type": "SoftwareApplication",
      "identifier": "checkmate",
      "name": "checkmate",
      "version": ">= 2.0.0",
      "provider": {
        "@id": "https://cran.r-project.org",
        "@type": "Organization",
        "name": "Comprehensive R Archive Network (CRAN)",
        "url": "https://cran.r-project.org"
      },
      "sameAs": "https://CRAN.R-project.org/package=checkmate"
    },
    {
      "@type": "SoftwareApplication",
      "identifier": "cli",
      "name": "cli",
      "version": ">= 3.1.0",
      "provider": {
        "@id": "https://cran.r-project.org",
        "@type": "Organization",
        "name": "Comprehensive R Archive Network (CRAN)",
        "url": "https://cran.r-project.org"
      },
      "sameAs": "https://CRAN.R-project.org/package=cli"
    },
    {
      "@type": "SoftwareApplication",
      "identifier": "dplyr",
      "name": "dplyr",
      "version": ">= 1.0.7",
      "provider": {
        "@id": "https://cran.r-project.org",
        "@type": "Organization",
        "name": "Comprehensive R Archive Network (CRAN)",
        "url": "https://cran.r-project.org"
      },
      "sameAs": "https://CRAN.R-project.org/package=dplyr"
    },
    {
      "@type": "SoftwareApplication",
      "identifier": "hms",
      "name": "hms",
      "version": ">= 1.1.1",
      "provider": {
        "@id": "https://cran.r-project.org",
        "@type": "Organization",
        "name": "Comprehensive R Archive Network (CRAN)",
        "url": "https://cran.r-project.org"
      },
      "sameAs": "https://CRAN.R-project.org/package=hms"
    },
    {
      "@type": "SoftwareApplication",
      "identifier": "lifecycle",
      "name": "lifecycle",
      "version": ">= 1.0.1",
      "provider": {
        "@id": "https://cran.r-project.org",
        "@type": "Organization",
        "name": "Comprehensive R Archive Network (CRAN)",
        "url": "https://cran.r-project.org"
      },
      "sameAs": "https://CRAN.R-project.org/package=lifecycle"
    },
    {
      "@type": "SoftwareApplication",
      "identifier": "lubridate",
      "name": "lubridate",
      "version": ">= 1.8.0",
      "provider": {
        "@id": "https://cran.r-project.org",
        "@type": "Organization",
        "name": "Comprehensive R Archive Network (CRAN)",
        "url": "https://cran.r-project.org"
      },
      "sameAs": "https://CRAN.R-project.org/package=lubridate"
    }
  ],
  "releaseNotes": "https://github.com/ropensci/mctq/blob/master/NEWS.md",
  "readme": "https://github.com/ropensci/mctq/blob/main/README.md",
  "fileSize": "672.353KB",
  "contIntegration": ["https://github.com/ropensci/mctq/actions", "https://app.codecov.io/gh/ropensci/mctq?branch=main"],
  "developmentStatus": ["https://www.repostatus.org/#active", "https://lifecycle.r-lib.org/articles/stages.html#maturing"],
  "review": {
    "@type": "Review",
    "url": "https://github.com/ropensci/software-review/issues/434",
    "provider": "https://ropensci.org"
  },
  "keywords": ["chronobiology", "mctq", "sleep", "r-package", "peer-reviewed", "r", "rstats"],
  "citation": [
    {
      "@type": "CreativeWork",
      "datePublished": "2021",
      "author": [
        {
          "@type": "Person",
          "givenName": "Daniel",
          "familyName": "Vartanian"
        },
        {
          "@type": "Person",
          "givenName": ["Ana", "Amelia"],
          "familyName": "Benedito-Silva"
        },
        {
          "@type": "Person",
          "givenName": "Mario",
          "familyName": "Pedrazzoli"
        }
      ],
      "name": "{mctq}: an R package for the Munich ChronoType Questionnaire",
      "url": "https://docs.ropensci.org/mctq/",
      "description": "Lifecycle: maturing"
    }
  ]
}
